pyimagetest/__init__.py
pyimagetest/_version.py
pyimagetest/py.typed
pyimagetest/backends/__init__.py
pyimagetest/backends/_imageio.py
pyimagetest/backends/_pil.py
pyimagetest/backends/_torchvision.py
pyimagetest-0.3.0.dist-info/LICENSE
pyimagetest-0.3.0.dist-info/METADATA
pyimagetest-0.3.0.dist-info/WHEEL
pyimagetest-0.3.0.dist-info/top_level.txt
pyimagetest-0.3.0.dist-info/RECORD
