Metadata-Version: 2.1
Name: pyimagetest
Version: 0.3.0
Summary: Short description of pyimagetest
Home-page: https://github.com/pmeier/pyimagetest
Author: Philip Meier
Author-email: github.pmeier@posteo.de
License: BSD-3-Clause
Project-URL: Source, https://github.com/pmeier/pyimagetest
Project-URL: Tracker, https://github.com/pmeier/pyimagetest/issues
Keywords: cookiecutter
Platform: any
Classifier: Development Status :: 4 - Beta
Classifier: License :: OSI Approved :: BSD License
Classifier: Programming Language :: Python :: 3.6
Classifier: Programming Language :: Python :: 3.7
Classifier: Programming Language :: Python :: 3.8
Classifier: Topic :: Software Development :: Testing
Classifier: Topic :: Utilities
Classifier: Typing :: Typed
Requires-Python: >=3.6
Requires-Dist: numpy
Provides-Extra: backends
Requires-Dist: imageio ; extra == 'backends'
Requires-Dist: Pillow ; extra == 'backends'
Requires-Dist: torchvision ; extra == 'backends'
